atp/__init__.py
atp/config.py
atp/middleware.py
atp/schemas.py
atp/settlement_client.py
atp_protocol-1.2.0.dist-info/LICENSE
atp_protocol-1.2.0.dist-info/METADATA
atp_protocol-1.2.0.dist-info/WHEEL
atp_protocol-1.2.0.dist-info/RECORD
