Metadata-Version: 2.3
Name: atp-protocol
Version: 1.2.0
Summary: ATP Protocol - Agentic Trade Protocol. The easiest way to enable agent-to-agent payments powered by Solana.
License: MIT
Keywords: atp,atp-protocol,solana,blockchain,cryptocurrency,payment-gated,agent-to-agent,agent payments,agent execution,payment settlement,solana payments,usdc,sol,fastapi,agent api,payment gateway,settlement service,agent marketplace,decentralized payments,web3,crypto payments,agent infrastructure,payment middleware,automated settlement
Author: The Swarm Corporation
Requires-Python: >=3.10,<4.0
Classifier: Development Status :: 4 - Beta
Classifier: Intended Audience :: Developers
Classifier: License :: OSI Approved :: MIT License
Classifier: Programming Language :: Python :: 3
Classifier: Programming Language :: Python :: 3.10
Classifier: Programming Language :: Python :: 3.11
Classifier: Programming Language :: Python :: 3.12
Classifier: Programming Language :: Python :: 3.13
Classifier: Topic :: Internet :: WWW/HTTP :: HTTP Servers
Classifier: Topic :: Office/Business :: Financial
Classifier: Topic :: Software Development :: Libraries :: Python Modules
Requires-Dist: fastapi
Requires-Dist: httpx
Requires-Dist: loguru
Requires-Dist: pydantic
Requires-Dist: python-dotenv
Requires-Dist: setuptools
Requires-Dist: starlette
Requires-Dist: swarms
Project-URL: Documentation, https://github.com/The-Swarm-Corporation/ATP-Protocol
Project-URL: Homepage, https://github.com/The-Swarm-Corporation/ATP-Protocol
Project-URL: Repository, https://github.com/The-Swarm-Corporation/ATP-Protocol
